cantileverwall/__init__.py
retainingwall_safety/__init__.py
retainingwall_safety-0.1.5.dist-info/LICENCE.txt
retainingwall_safety-0.1.5.dist-info/LICENSE
retainingwall_safety-0.1.5.dist-info/METADATA
retainingwall_safety-0.1.5.dist-info/WHEEL
retainingwall_safety-0.1.5.dist-info/top_level.txt
retainingwall_safety-0.1.5.dist-info/RECORD
