Metadata-Version: 2.1
Name: retainingwall_safety
Version: 0.1.5
Summary: Library for calculating safety factors of cantilever retaining walls
Home-page: https://github.com/semihyumusak/RetainingWallSafetyEvaluator
Author: Semih Yumuşak
Author-email: semihyumusak@yahoo.com
License: MIT
Keywords: cantilever wall,geotechnical engineering,safety factors,sliding,overturning,slope stability
Classifier: Development Status :: 4 - Beta
Classifier: Intended Audience :: Science/Research
Classifier: Intended Audience :: Education
Classifier: License :: OSI Approved :: MIT License
Classifier: Programming Language :: Python :: 3
Classifier: Topic :: Scientific/Engineering
License-File: LICENCE.txt
License-File: LICENSE
Requires-Dist: numpy
Requires-Dist: scipy
